README.rst
setup.py
urwid_viedit/__init__.py
urwid_viedit/viedit.py
urwid_viedit.egg-info/PKG-INFO
urwid_viedit.egg-info/SOURCES.txt
urwid_viedit.egg-info/dependency_links.txt
urwid_viedit.egg-info/requires.txt
urwid_viedit.egg-info/top_level.txt