Metadata-Version: 1.2
Name: urwid-viedit
Version: 0.1.2
Summary: Edit widget supporting vi-mode and emacs keybindings
Home-page: https://github.com/laktak/urwid_viedit
Author: Christian Zangl
Author-email: laktak@cdak.net
License: MIT
Platform: UNKNOWN
Requires-Python: >=3.6.0
